LICENSE
MANIFEST.in
README.md
README.txt
setup.py
juju_suspend/__init__.py
juju_suspend/cli.py
juju_suspend/environment.py
juju_suspend.egg-info/PKG-INFO
juju_suspend.egg-info/SOURCES.txt
juju_suspend.egg-info/dependency_links.txt
juju_suspend.egg-info/entry_points.txt
juju_suspend.egg-info/requires.txt
juju_suspend.egg-info/top_level.txt
juju_suspend/providers/__init__.py
juju_suspend/providers/base.py
juju_suspend/providers/local.py
juju_suspend/providers/openstack.py