Metadata-Version: 1.1
Name: juju-suspend
Version: 0.1.0
Summary: UNKNOWN
Home-page: UNKNOWN
Author: Jorge Niedbalski R.
Author-email: jnr@metaklass.org
License: UNKNOWN
Platform: UNKNOWN
Classifier: Development Status :: 3 - Alpha
